{
    "WCT-055CDD73-2998-4D29-8F55-9969A7C61C10": {
        "customer_email": "wagner123castro@gmail.com",
        "customer_name": "Wagner32871793816",
        "expiration_date": "2124-09-08",
        "machine_id": "fa83507ec0ddf5fdb7cf897097b54c6c05878c82e4df84dcc66ff4837d3b9dff",
        "plan": "Vitalício",
        "start_date": "2025-10-02",
        "status": "active",
        "value": 0.0
    },
    "WCT-2FC197C0-9F9D-4ADC-A841-3B88B53A1293": {
        "customer_email": "wagner123catro@gmasil.com",
        "customer_name": "Wagner",
        "expiration_date": null,
        "machine_id": null,
        "plan": "Vitalício",
        "start_date": null,
        "status": "inactive",
        "value": 0.0
    },
    "WCT-4DA70CBC-76D3-492E-9657-618C982671E1": {
        "customer_email": "wagner123castro@gmail.com",
        "customer_name": "32871793816WagnerCastro",
        "expiration_date": "2124-09-04",
        "machine_id": "018539cfd01ba3a16be5a30419e8768f580675295ceeec9bb552f58615695c55",
        "plan": "Vitalício",
        "start_date": "2025-09-28",
        "status": "active",
        "value": 0.0
    },
    "WCT-4EC46444-937C-4406-9D63-DD661098272A": {
        "customer_email": "wagner123castro@gmail.com",
        "customer_name": "Wagner Castro",
        "expiration_date": null,
        "machine_id": null,
        "plan": "Vitalício",
        "start_date": null,
        "status": "inactive",
        "value": 0.0
    },
    "WCT-59F56A02-F676-4515-BD79-8E9BE8BDC555": {
        "customer_email": "wagnwe123castro@gmail.com",
        "customer_name": "32871793816wagnercastro",
        "expiration_date": "2124-09-02",
        "machine_id": "ba941bbc8bd63bddb440093ad5f459f40f8d6d6ff297ab9bc560651114e4c861",
        "plan": "Vitalício",
        "start_date": "2025-09-26",
        "status": "active",
        "value": 0.0
    },
    "WCT-5AA8E3D3-BC9A-4A4F-9639-050A659A6126": {
        "customer_email": "wagner123castro@gmail.com",
        "customer_name": "castro wagner",
        "expiration_date": "2124-09-08",
        "machine_id": "55e701350d0f83bd9ab5e75a57671a9a01d40a1c9bb251c51fe1d85f533d4dc5",
        "plan": "Vitalício",
        "start_date": "2025-10-02",
        "status": "active",
        "value": 0.0
    },
    "WCT-6B9AE1AF-F2E1-4F64-94DD-6E60160B8158": {
        "customer_email": "caroll.reis@hotmail.com",
        "customer_name": "Caroline Reis",
        "expiration_date": null,
        "machine_id": null,
        "plan": "Mensal",
        "start_date": null,
        "status": "inactive",
        "value": 150.0
    },
    "WCT-78E4F4F3-4DAF-4948-AE8E-C9114E0A046F": {
        "customer_email": "wagner123castro@gmail.cpom",
        "customer_name": "wagnertestes",
        "expiration_date": "2124-09-08",
        "machine_id": "55e701350d0f83bd9ab5e75a57671a9a01d40a1c9bb251c51fe1d85f533d4dc5",
        "plan": "Vitalício",
        "start_date": "2025-10-02",
        "status": "active",
        "value": 0.0
    },
    "WCT-C48D3187-B4FE-4C3A-B0BE-21C159481DC7": {
        "customer_email": "wagner123castro@gmail.com",
        "customer_name": "32871793816WagnerCastro",
        "expiration_date": null,
        "machine_id": null,
        "plan": "Vitalício",
        "start_date": null,
        "status": "inactive",
        "value": 0.0
    },
    "WCT-E1F4638F-C0B6-45CF-87D1-8A0DE39FB51A": {
        "customer_email": "wagner123castro@gmail.com",
        "customer_name": "Wagne Castro",
        "expiration_date": null,
        "machine_id": null,
        "plan": "Vitalício",
        "start_date": null,
        "status": "inactive",
        "value": 0.0
    },
    "WCT-F1B22972-DECF-40D8-AB68-144E33872EB1": {
        "customer_email": "wagner123castro@gmail.com",
        "customer_name": "Wagner 2",
        "expiration_date": null,
        "machine_id": null,
        "plan": "Vitalício",
        "start_date": null,
        "status": "inactive",
        "value": 0.0
    },
    "WCT-F6F7C75E-2E9A-493A-B009-878324D63055": {
        "customer_email": "wagner123castro@gmail.com",
        "customer_name": "Wagner",
        "customer_phone": "11988105900",
        "expiration_date": null,
        "machine_id": null,
        "plan": "Vitalício",
        "start_date": null,
        "status": "inactive",
        "value": 0.0
    },
    "WCT-FF1207A7-9658-4ED7-B60F-BE3AC1C8E2C4": {
        "customer_email": "wanger123castro@gmail.com",
        "customer_name": "Wagner Castro",
        "expiration_date": null,
        "machine_id": null,
        "plan": "Vitalício",
        "start_date": null,
        "status": "inactive",
        "value": 0.0
    },
    "WCT-4F2D2A85-C18A-4AC0-A09C-C594442A11AE": {
        "status": "active",
        "machine_id": "3d82da0661c5d6054893125f37ded4471c613bee8ec06ae4b353046cc2f44129",
        "start_date": "2025-10-03",
        "expiration_date": "2124-09-09",
        "customer_name": "Wagner Castro",
        "customer_email": "wagner123castro@gmail.com",
        "plan": "Vitalício",
        "value": 0.0,
        "customer_phone": "11988105900"
    }
}